reddepy/redde.py
reddepy-1.0.0.dist-info/LICENSE
reddepy-1.0.0.dist-info/METADATA
reddepy-1.0.0.dist-info/WHEEL
reddepy-1.0.0.dist-info/entry_points.txt
reddepy-1.0.0.dist-info/top_level.txt
reddepy-1.0.0.dist-info/RECORD
