Metadata-Version: 2.1
Name: reddepy
Version: 1.0.0
Summary: A Python package that allows merchants to receive, send, check transaction status, and perform lots of payment transactions using Redde payment API.
Home-page: https://github.com/wigalsolutionsltd/reddePy
Author: Richard Asante
Author-email: ricardo.volvox@gmail.com
License: MIT
Platform: UNKNOWN
Classifier: License :: OSI Approved :: MIT License
Classifier: Programming Language :: Python :: 3
Classifier: Programming Language :: Python :: 3.7
Requires-Dist: requests
